{
  "dropdown": {
    "background-color": {
      "value": "{theme.color.background.canvas}",
      "type": "color"
    },
    "border-color": {
      "value": "{theme.color.background.surface}",
      "type": "color"
    },
    "no-background": {
      "value": "{core.color.transparent}",
      "type": "color"
    },
    "underline-color": {
      "value": "{theme.color.actions.disabled.amplified}",
      "type": "color"
    },
    "action-color": {
      "value": "{theme.color.text.subtle}",
      "type": "color"
    },
    "text-color": {
      "value": "{theme.color.text.subtle}",
      "type": "color"
    },
    "icon-color": {
      "value": "{theme.color.text.muted}",
      "type": "color"
    },
    "hover": {
      "background-color": {
        "value": "{theme.color.actions.primary.subtle}",
        "type": "color"
      }
    },
    "active": {
      "background-color": {
        "value": "{theme.color.background.surface}",
        "type": "color"
      }
    },
    "disabled": {
      "action-color": {
        "value": "{theme.color.actions.disabled.muted}",
        "type": "color"
      }
    },
    "border-radius": {
      "value": "{theme.ui.border-radius.sm}",
      "type": "borderRadius"
    },
    "shadow": {
      "value": "{core.depth.plus1}",
      "type": "boxShadow"
    },
    "no-shadow": {
      "value": "{core.depth.none}",
      "type": "boxShadow"
    },
    "border-width": {
      "value": "{core.border-width.1}",
      "type": "borderWidth"
    },
    "no-border": {
      "value": "{core.border-width.0}",
      "type": "borderWidth"
    },
    "padding-left": {
      "value": "{core.space.plus2}",
      "type": "spacing"
    },
    "padding-right": {
      "value": "{core.space.plus2}",
      "type": "spacing"
    },
    "font": {
      "value": {
        "fontFamily": "{theme.font.family.body}",
        "fontWeight": "{theme.font.weight.regular}",
        "fontSize": "{theme.font.size.sm}",
        "lineHeight": "{theme.font.lineheight.sm}"
      },
      "type": "typography"
    }
  }
}